{"cameraMode":{"drawMode":0,"name":"Shaded","section":"Shading Mode"},"sceneLighting":true,"audioPlay":false,"sceneViewState":{"m_AlwaysRefresh":false,"showFog":true,"showSkybox":true,"showFlares":true,"showImageEffects":true,"showParticleSystems":true,"showVisualEffectGraphs":true,"m_FxEnabled":true},"in2DMode":false,"pivot":{"x":-2.924055337905884,"y":9.740396499633789,"z":8.37201976776123},"rotation":{"x":-0.21308860182762147,"y":0.025493714958429338,"z":-0.00556215550750494,"w":-0.9766836762428284},"size":10.304065704345704,"orthographic":false}